README.rst
setup.py
django_markdownplus.egg-info/PKG-INFO
django_markdownplus.egg-info/SOURCES.txt
django_markdownplus.egg-info/dependency_links.txt
django_markdownplus.egg-info/requires.txt
django_markdownplus.egg-info/top_level.txt
markdownplus/__init__.py
markdownplus/markdown.py
markdownplus/templatetags/__init__.py
markdownplus/templatetags/markdownplus.py