Metadata-Version: 1.1
Name: django-markdownplus
Version: 0.1.2
Summary: tiny django app for supporting markdown template tag
Home-page: https://github.com/makerj/django_markdownplus
Author: makerj
Author-email: ohenwkgdj@gmail.com
License: The MIT License (MIT)
